reap_protocol/__init__.py
reap_protocol/client.py
reap_protocol-0.1.3.dist-info/METADATA
reap_protocol-0.1.3.dist-info/WHEEL
reap_protocol-0.1.3.dist-info/top_level.txt
reap_protocol-0.1.3.dist-info/RECORD
