Metadata-Version: 2.4
Name: reap-protocol
Version: 0.1.3
Summary: Official SDK for the Reap Protocol: Agentic Commerce Grid
Project-URL: Homepage, https://protocol.reap.deals
Project-URL: Documentation, https://docs.reap.deals
Project-URL: Source, https://github.com/Apriloracle/Reap-protocol-sdk
Requires-Python: >=3.7
Requires-Dist: requests
Requires-Dist: web3
